{
  "title": "شقة للبيع - الحي السابع",
  "price": "4,000,000 جنيه",
  "area": "180 م²",
  "rooms": 3,
  "bathrooms": null,
  "floor": 10,
  "elevator": true,
  "garage": null,
  "finish": "نصف تشطيب",
  "view": "واجهة بحرية تطل على الحديقة الدولية",
  "location": "شارع السويس 19، الحي السابع – مدينة نصر",
  "description": "شقة جاهزة للسكن بتشطيب نصف فرش، موقع مميز وإطلالة خلابة على الحديقة الدولية، مزودة بـ 3 تكييفات وسخانات حديثة.",
  "date": "2025-07-01",
  "images": [],
  "page_url": "/property-7th-district.html"
  "story": "price_drop"
}
