{
  "title": "شقة للبيع – 112م – كومبوند جولدن سيتي – شرق مدينة نصر",
  "price": "2,250,000 جنيه",
  "area": "112 م²",
  "rooms": 3,
  "bathrooms": 1,
  "floor": 1,
  "elevator": true,
  "garage": false,
  "finish": "نصف تشطيب",
  "direction": "واجهة أمامية مشرقة",
  "description": "فرصة رائعة لامتلاك شقة في موقع مميز بكومبوند جولدن سيتي – حي شرق مدينة نصر. الشقة واجهة، بمساحة مثالية وتشطيب مرن حسب الرغبة. مناسبة للسكن أو الاستثمار في منطقة راقية.",
  "date": "2025-07-22",
  "more_details": "العقار في عمارة رقم 7 – عقد نهائي ومرخص – الدور الأول – يوجد جراج خاص بالبدروم بسعر منفصل 350,000 جنيه. المعاينة متاحة للجادين بالتنسيق عبر الرقم: 00201126729529. الكمبوند على الطوب الرملي وموقعه استراتيجي."
}
