{
  "id": "ahly-club-fursan-320m",
  "title": "ุดูุฉ 320ู ููู ุงููุงุฏู ุงูุฃููู ูุจุงุดุฑุฉ - ุนูุงุฑุฉ ุงููุฑุณุงู",
  "date": "2025-11-29",
  "location": "ุฃูุงู ุงููุงุฏู ุงูุฃููู ูุจุงุดุฑุฉ - ุนูุงุฑุฉ ุงููุฑุณุงู ุงูุดููุฑุฉ",
  "price": "13,000,000 ุฌููู",
  "price_display": "13,000,000 ุฌ.ู (ุดุงูู ุงููุฑุด ูุงูุชููููุงุช)",
  "area": "320 ูุชุฑ ูุฑุจุน",
  "rooms": "4 ุบุฑู ููู (ูุณุงุญุงุช ููููุฉ)",
  "bathrooms": "3 ุญูุงู ูุงุฎุฑ",
  "floor": "ุงูุฏูุฑ ุงูุณุงุฏุณ (ููู ุจุงููุฑุงูุง)",
  "elevator": true,
  "garage": true,
  "finish": "ุงูุชุฑุง ุณูุจุฑ ูููุณ (ูุฑุด ููุฏูู)",
  "summary": "ุนููุงู ุงูุตููุฉ ุจูุฏููุฉ ูุตุฑ. ููู ููุชูุญ ุนูู ุงููุงุฏู ุงูุฃูููุ ุชุจุงุน ุจุงููุฑุด.",
  "description": "ููู ูุจุญุซ ุนู ุงูุชููุฒ ุงูุงุฌุชูุงุนู ูุงูุฑูุงููุฉ. ุดูุฉ ูู ูุงุญุฏุฉ ูู ุฃุดูุฑ ุนูุงุฑุงุช ูุฏููุฉ ูุตุฑ (ุงููุฑุณุงู).\n\n๐ ุงูุฑูุงููุฉ ุงููุทููุฉ:\n- ุฅุทูุงูุฉ ูุจุงุดุฑุฉ ูููุชูุญุฉ ุนูู ุงููุงุฏู ุงูุฃููู (ุบูุฑ ูุฌุฑูุญุฉ ููุงุฆูุงู).\n- ูุณุงุญุฉ 320 ูุชุฑ ุชููุญู ุฅุญุณุงุณ ุงููููุง.\n- ุชุจุงุน ุจุงููุงูู ุจุงููุฑุด ุงููุงุฎุฑ ูุงูุชููููุงุช (Ready to Move).\n\n๐ข ุงูุนูุงุฑุฉ:\nูุฏุฎู ููุฏูู ูููู ุจุงูุฒูุงุฑุ ุฃูู ูุญุฑุงุณุฉุ ูุฌุฑุงุฌ ุฎุงุต.",
  "extra_details": "ูููุน ูุง ูุชูุฑุฑ - ุงูุณุนุฑ ุดุงูู ูู ุดูุก - ุงุณุชูุงู ููุฑู.",
  "images": [],
  "page_url": "/property-ahly-club-fursan"
}
